plantilla/__init__.py
plantilla/styles/mecon.mplstyle
plantilla-0.0.10.dist-info/METADATA
plantilla-0.0.10.dist-info/WHEEL
plantilla-0.0.10.dist-info/top_level.txt
plantilla-0.0.10.dist-info/RECORD
