Metadata-Version: 2.1
Name: plantilla
Version: 0.0.10
Summary: UNKNOWN
License: UNKNOWN
Platform: UNKNOWN
Requires-Dist: matplotlib (>=2.0.0)
